aiowebostv/__init__.py
aiowebostv/buttons.py
aiowebostv/endpoints.py
aiowebostv/exceptions.py
aiowebostv/handshake.py
aiowebostv/models.py
aiowebostv/py.typed
aiowebostv/webos_client.py
aiowebostv-0.7.5.dist-info/licenses/LICENSE
aiowebostv-0.7.5.dist-info/METADATA
aiowebostv-0.7.5.dist-info/WHEEL
aiowebostv-0.7.5.dist-info/top_level.txt
aiowebostv-0.7.5.dist-info/RECORD
