Metadata-Version: 2.4
Name: aiowebostv
Version: 0.7.5
Summary: Library to control webOS based LG TV devices
Author-email: Home Assistant Team <hello@home-assistant.io>
License-Expression: Apache-2.0
Project-URL: Source code, https://github.com/home-assistant-libs/aiowebostv
Classifier: Development Status :: 4 - Beta
Classifier: Intended Audience :: Developers
Classifier: Natural Language :: English
Classifier: Programming Language :: Python :: 3
Classifier: Programming Language :: Python :: 3.11
Classifier: Programming Language :: Python :: 3.12
Classifier: Programming Language :: Python :: 3.13
Classifier: Topic :: Home Automation
Requires-Python: >=3.11
License-File: LICENSE
Requires-Dist: aiohttp>=3.11
Dynamic: license-file
